llama_index/llms/text_generation_inference/__init__.py
llama_index/llms/text_generation_inference/base.py
llama_index/llms/text_generation_inference/utils.py
llama_index_llms_text_generation_inference-0.3.3.dist-info/METADATA
llama_index_llms_text_generation_inference-0.3.3.dist-info/WHEEL
llama_index_llms_text_generation_inference-0.3.3.dist-info/licenses/LICENSE
llama_index_llms_text_generation_inference-0.3.3.dist-info/RECORD
