Metadata-Version: 2.4
Name: llama-index-llms-text-generation-inference
Version: 0.3.3
Summary: llama-index llms huggingface text generation inference integration
Author-email: Your Name <you@example.com>
License-Expression: MIT
License-File: LICENSE
Requires-Python: <4.0,>=3.9
Requires-Dist: llama-index-core<0.13,>=0.12.0
Requires-Dist: llama-index-utils-huggingface<0.4,>=0.3.0
Requires-Dist: tgi<3,>=2.0.0
